multipart_form_data_conformance/__init__.py
multipart_form_data_conformance/manifest.json
multipart_form_data_conformance/schema/headers.schema.json
multipart_form_data_conformance/schema/parsed-result.schema.json
multipart_form_data_conformance/schema/test-case.schema.json
multipart_form_data_conformance/tests/basic/001-single-text-field/headers.json
multipart_form_data_conformance/tests/basic/001-single-text-field/input.raw
multipart_form_data_conformance/tests/basic/001-single-text-field/test.json
multipart_form_data_conformance/tests/basic/002-single-file/headers.json
multipart_form_data_conformance/tests/basic/002-single-file/input.raw
multipart_form_data_conformance/tests/basic/002-single-file/test.json
multipart_form_data_conformance/tests/basic/003-multiple-fields/headers.json
multipart_form_data_conformance/tests/basic/003-multiple-fields/input.raw
multipart_form_data_conformance/tests/basic/003-multiple-fields/test.json
multipart_form_data_conformance/tests/basic/004-mixed-fields-files/headers.json
multipart_form_data_conformance/tests/basic/004-mixed-fields-files/input.raw
multipart_form_data_conformance/tests/basic/004-mixed-fields-files/test.json
multipart_form_data_conformance/tests/basic/005-multiple-files-same-name/headers.json
multipart_form_data_conformance/tests/basic/005-multiple-files-same-name/input.raw
multipart_form_data_conformance/tests/basic/005-multiple-files-same-name/test.json
multipart_form_data_conformance/tests/boundaries/040-simple-boundary/headers.json
multipart_form_data_conformance/tests/boundaries/040-simple-boundary/input.raw
multipart_form_data_conformance/tests/boundaries/040-simple-boundary/test.json
multipart_form_data_conformance/tests/boundaries/041-boundary-with-hyphens/headers.json
multipart_form_data_conformance/tests/boundaries/041-boundary-with-hyphens/input.raw
multipart_form_data_conformance/tests/boundaries/041-boundary-with-hyphens/test.json
multipart_form_data_conformance-0.1a0.dist-info/METADATA
multipart_form_data_conformance-0.1a0.dist-info/WHEEL
multipart_form_data_conformance-0.1a0.dist-info/licenses/LICENSE
multipart_form_data_conformance-0.1a0.dist-info/RECORD
