Metadata-Version: 2.4
Name: multipart-form-data-conformance
Version: 0.1a0
Summary: Language-independent conformance test suite for multipart/form-data parsing and generation
Project-URL: Homepage, https://github.com/simonw/multipart-form-data-conformance
Project-URL: Repository, https://github.com/simonw/multipart-form-data-conformance
License-Expression: MIT
License-File: LICENSE
Keywords: conformance,form-data,http,multipart,testing
Classifier: Development Status :: 3 - Alpha
Classifier: Intended Audience :: Developers
Classifier: Programming Language :: Python :: 3
Classifier: Programming Language :: Python :: 3.10
Classifier: Programming Language :: Python :: 3.11
Classifier: Programming Language :: Python :: 3.12
Classifier: Programming Language :: Python :: 3.13
Classifier: Programming Language :: Python :: 3.14
Classifier: Topic :: Internet :: WWW/HTTP
Classifier: Topic :: Software Development :: Testing
Requires-Python: >=3.10
